mcp/__init__.py
mcp/api.py
mcp/cards.py
mcp/chm.py
mcp/config.py
mcp/html_parser.py
mcp/logging_utils.py
mcp/models.py
mcp/paths.py
mcp/reflection.py
mcp/scoring.py
mcp/serialization.py
mcp/text_utils.py
mcp/vocabulary.py
sap2000_python_api-0.1.1.dist-info/METADATA
sap2000_python_api-0.1.1.dist-info/WHEEL
sap2000_python_api-0.1.1.dist-info/top_level.txt
sap2000_python_api-0.1.1.dist-info/RECORD
