Metadata-Version: 2.4
Name: sap2000-python-api
Version: 0.1.1
Summary: Pipeline for building SAP2000 OAPI model context protocol assets.
Author: MCP Team
Requires-Python: >=3.11
Requires-Dist: beautifulsoup4>=4.12.0
Requires-Dist: lxml>=4.9.0
Requires-Dist: pythonnet==3.0.3
Requires-Dist: fastapi>=0.110.0
Requires-Dist: uvicorn[standard]>=0.29.0
Provides-Extra: dev
Requires-Dist: pytest>=7.4; extra == "dev"
Requires-Dist: pytest-cov>=4.1; extra == "dev"
Requires-Dist: black>=24.3; extra == "dev"
Requires-Dist: mypy>=1.9; extra == "dev"
